blockmatrix/__init__.py
blockmatrix/blockmatrix.py
blockmatrix-0.3.0.dist-info/LICENSE
blockmatrix-0.3.0.dist-info/METADATA
blockmatrix-0.3.0.dist-info/WHEEL
blockmatrix-0.3.0.dist-info/RECORD
