Metadata-Version: 2.3
Name: blockmatrix
Version: 0.3.0
Summary: Utilities to handle blockmatrices, especially covariance matrices.
License: BSD-3-Clause
Keywords: block matrix,numpy,spatio-temporal data
Author: Jan Sosulski
Author-email: mail@jan-sosulski.de
Requires-Python: >=3.9,<4.0
Classifier: License :: OSI Approved :: BSD License
Classifier: Programming Language :: Python :: 3
Classifier: Programming Language :: Python :: 3.9
Classifier: Programming Language :: Python :: 3.10
Classifier: Programming Language :: Python :: 3.11
Classifier: Programming Language :: Python :: 3.12
Classifier: Programming Language :: Python :: 3.13
Provides-Extra: solver
Requires-Dist: numpy (>=1,<2)
Requires-Dist: toeplitz (>=0.3.2,<0.4.0) ; extra == "solver"
Project-URL: Homepage, https://github.com/jsosulski/blockmatrix
Project-URL: Repository, https://github.com/jsosulski/blockmatrix
